scb_tools
