Metadata-Version: 2.1
Name: scbtools
Version: 0.0.6
Summary: Personal Tools
Home-page: UNKNOWN
Author: shenchenbin
Author-email: 18390210785@163.com
License: UNKNOWN
Platform: UNKNOWN
Classifier: Programming Language :: Python :: 3
Classifier: License :: OSI Approved :: MIT License
Classifier: Operating System :: OS Independent
